retgit/__init__.py
retgit/cli.py
retgit/commands/__init__.py
retgit/commands/init.py
retgit/commands/integration.py
retgit/commands/plugin.py
retgit/commands/propose.py
retgit/commands/push.py
retgit/core/config.py
retgit/core/gitops.py
retgit/core/llm.py
retgit/core/llm_providers.json
retgit/core/prompt.py
retgit/integrations/__init__.py
retgit/integrations/base.py
retgit/integrations/github.py
retgit/integrations/install_schemas.json
retgit/integrations/jira.py
retgit/integrations/registry.py
retgit/plugins/__init__.py
retgit/plugins/base.py
retgit/plugins/laravel.py
retgit/plugins/registry.py
retgit/plugins/changelog/__init__.py
retgit/plugins/changelog/commands.py
retgit/plugins/version/__init__.py
retgit/plugins/version/commands.py
retgit/prompts/__init__.py
retgit/prompts/default.md
retgit/prompts/minimal.md
retgit/utils/__init__.py
retgit/utils/console.py
retgit/utils/editor.py
retgit/utils/security.py
retgit-0.2.0.dist-info/licenses/LICENSE
retgit-0.2.0.dist-info/METADATA
retgit-0.2.0.dist-info/WHEEL
retgit-0.2.0.dist-info/entry_points.txt
retgit-0.2.0.dist-info/top_level.txt
retgit-0.2.0.dist-info/RECORD
