Metadata-Version: 2.4
Name: retgit
Version: 0.2.0
Summary: AI-powered Git workflow assistant with task management integration
Author-email: Your Name <your.email@example.com>
License-Expression: MIT
Project-URL: Homepage, https://github.com/ertiz82/retgit
Project-URL: Documentation, https://github.com/ertiz82/retgit#readme
Project-URL: Repository, https://github.com/ertiz82/retgit.git
Project-URL: Issues, https://github.com/ertiz82/retgit/issues
Keywords: git,commit,ai,jira,automation,workflow,task-management
Classifier: Development Status :: 4 - Beta
Classifier: Environment :: Console
Classifier: Intended Audience :: Developers
Classifier: Operating System :: OS Independent
Classifier: Programming Language :: Python :: 3
Classifier: Programming Language :: Python :: 3.9
Classifier: Programming Language :: Python :: 3.10
Classifier: Programming Language :: Python :: 3.11
Classifier: Programming Language :: Python :: 3.12
Classifier: Programming Language :: Python :: 3.13
Classifier: Programming Language :: Python :: 3.14
Classifier: Topic :: Software Development :: Version Control :: Git
Classifier: Topic :: Software Development :: Build Tools
Requires-Python: >=3.9
License-File: LICENSE
Requires-Dist: typer>=0.12.0
Requires-Dist: rich>=13.0.0
Requires-Dist: PyYAML>=6.0
Requires-Dist: GitPython>=3.1.0
Requires-Dist: requests>=2.31.0
Dynamic: license-file
